voxtalkz/__init__.py
voxtalkz/__main__.py
voxtalkz/voxtalkz.py
voxtalkz-1.2.9.dist-info/LICENSE
voxtalkz-1.2.9.dist-info/METADATA
voxtalkz-1.2.9.dist-info/WHEEL
voxtalkz-1.2.9.dist-info/top_level.txt
voxtalkz-1.2.9.dist-info/RECORD
