Metadata-Version: 2.1
Name: voxtalkz
Version: 1.2.9
Summary: Text To Audio Drama (TTAD) program, uses play-like scripts.
Home-page: https://github.com/DonFlymoor/voxTalkz
Author: Don Flymoor
Author-email: donflymoor@gmail.com
License: GNU GPL
Platform: UNKNOWN
Classifier: License :: OSI Approved :: GNU General Public License (GPL)
Classifier: Programming Language :: Python
Classifier: Programming Language :: Python :: 3
Classifier: Programming Language :: Python :: 3.6
Classifier: Programming Language :: Python :: Implementation :: CPython
Classifier: Programming Language :: Python :: Implementation :: PyPy
Requires-Python: >=3.6.0
Requires-Dist: pydub
Requires-Dist: gTTS
